authzed_client/__init__.py
authzed_client/api/__init__.py
authzed_client/api/experimental_service/__init__.py
authzed_client/api/experimental_service/experimental_service_bulk_check_permission.py
authzed_client/api/experimental_service/experimental_service_bulk_export_relationships.py
authzed_client/api/experimental_service/experimental_service_bulk_import_relationships.py
authzed_client/api/permissions_service/__init__.py
authzed_client/api/permissions_service/permissions_service_check_permission.py
authzed_client/api/permissions_service/permissions_service_delete_relationships.py
authzed_client/api/permissions_service/permissions_service_expand_permission_tree.py
authzed_client/api/permissions_service/permissions_service_lookup_resources.py
authzed_client/api/permissions_service/permissions_service_lookup_subjects.py
authzed_client/api/permissions_service/permissions_service_read_relationships.py
authzed_client/api/permissions_service/permissions_service_write_relationships.py
authzed_client/api/schema_service/__init__.py
authzed_client/api/schema_service/schema_service_read_schema.py
authzed_client/api/schema_service/schema_service_write_schema.py
authzed_client/api/watch_resources_service/__init__.py
authzed_client/api/watch_resources_service/watch_resources_service_watch_resources.py
authzed_client/api/watch_service/__init__.py
authzed_client/api/watch_service/watch_service_watch.py
authzed_client/client.py
authzed_client/errors.py
authzed_client/models/__init__.py
authzed_client/models/apiv_1_alpha_1_read_schema_response.py
authzed_client/models/apiv_1_alpha_1_write_schema_response.py
authzed_client/models/apiv_1_read_schema_request.py
authzed_client/models/apiv_1_read_schema_response.py
authzed_client/models/apiv_1_write_schema_request.py
authzed_client/models/apiv_1_write_schema_response.py
authzed_client/models/delete_relationships_response_deletion_progress.py
authzed_client/models/developer_error_error_kind.py
authzed_client-1.0.1.dist-info/METADATA
authzed_client-1.0.1.dist-info/WHEEL
authzed_client-1.0.1.dist-info/RECORD
